<odoo>
    <data>
        <template id="spiralworld_summit_home_menu" name="SprialWorld Summit menu">
            <hr/>
            <div class="row" style="text-align: center;">
                <div class="col-md-3">
                    <img class="card-img-top center" src="spiralworld_summit_web/static/assets/images/schedule.PNG"
                         style="height: 100px; width: 100px;" alt="Card image cap"/>
                    <div class="card-body">
                        <h5 class="card-title">Schedule</h5>
                        <p class="card-text">Some quick example text to build on the card title and
                            make up the bulk of the card's content.
                        </p>

                    </div>
                </div>
                <p></p>
                <div class="col-md-3">
                    <img class="card-img-center center" src="spiralworld_summit_web/static/assets/images/Webinar.png"
                         style="height: 100px; width: 100px;" alt="Card image cap"/>
                    <div class="card-body">
                        <h5 class="card-title">Webinar</h5>
                        <p class="card-text">Some quick example text to build on the card title and
                            make up the bulk of the card's content.
                        </p>

                    </div>
                </div>
                <div class="col-md-3">
                    <img class="card-img-top center" src="spiralworld_summit_web/static/assets/images/b2b-.png"
                         style="height: 100px; width: 100px;" alt="Card image cap"/>
                    <div class="card-body">
                        <h5 class="card-title">B2B Zone</h5>
                        <p class="card-text">Some quick example text to build on the card title and
                            make up the bulk of the card's content.
                        </p>

                    </div>
                </div>
                <div class="col-md-3">
                    <img class="card-img-top center" src="spiralworld_summit_web/static/assets/images/Expo Zone.png"
                         style="height: 100px; width: 100px;" alt="Card image cap"/>
                    <div class="card-body">
                        <h5 class="card-title">Expo Zone</h5>
                        <p class="card-text">Some quick example text to build on the card title and
                            make up the bulk of the card's content.
                        </p>

                    </div>
                </div>
            </div>

        </template>
    </data>
</odoo>
